fs/opener/sshfs.py
fs/sshfs/__init__.py
fs/sshfs/_version.txt
fs/sshfs/error_tools.py
fs/sshfs/file.py
fs/sshfs/sshfs.py
fs.sshfs-1.0.2.dist-info/COPYING
fs.sshfs-1.0.2.dist-info/METADATA
fs.sshfs-1.0.2.dist-info/WHEEL
fs.sshfs-1.0.2.dist-info/entry_points.txt
fs.sshfs-1.0.2.dist-info/top_level.txt
fs.sshfs-1.0.2.dist-info/zip-safe
fs.sshfs-1.0.2.dist-info/RECORD
